neuromodex_vnet_dbs/__init__.py
neuromodex_vnet_dbs/core/BaseProcessor.py
neuromodex_vnet_dbs/core/__init__.py
neuromodex_vnet_dbs/data/__init__.py
neuromodex_vnet_dbs/data/postprocessing.py
neuromodex_vnet_dbs/data/preprocessing.py
neuromodex_vnet_dbs/data/sitk_image_handler.py
neuromodex_vnet_dbs/data/sitk_transform.py
neuromodex_vnet_dbs/models/CNNBasedSegmentationModel.py
neuromodex_vnet_dbs/models/ConductivityMapper.py
neuromodex_vnet_dbs/models/GMM.py
neuromodex_vnet_dbs/models/ProbabilisticBasedSegmentationModel.py
neuromodex_vnet_dbs/models/SegmentationModelBase.py
neuromodex_vnet_dbs/models/__init__.py
neuromodex_vnet_dbs/models/architecture/VNet.py
neuromodex_vnet_dbs/models/architecture/__init__.py
neuromodex_vnet_dbs/pipelines/ConductivityProcessingPipeline.py
neuromodex_vnet_dbs/pipelines/SegmentationPipeline.py
neuromodex_vnet_dbs/pipelines/__init__.py
neuromodex_vnet_dbs/slicer/__init__.py
neuromodex_vnet_dbs/slicer/slicer_install_plugin.py
neuromodex_vnet_dbs/slicer/BrainSegmentation/BrainSegmentation.py
neuromodex_vnet_dbs/slicer/BrainSegmentation/BrainSegmentation.xml
neuromodex_vnet_dbs/slicer/BrainSegmentation/__init__.py
neuromodex_vnet_dbs/slicer/ConductivityMapping/ConductivityMapping.py
neuromodex_vnet_dbs/slicer/ConductivityMapping/ConductivityMapping.xml
neuromodex_vnet_dbs/slicer/ConductivityMapping/__init__.py
neuromodex_vnet_dbs/weights/SpacingAwareVNetS/best.pth
neuromodex_vnet_dbs-0.2.0.dist-info/METADATA
neuromodex_vnet_dbs-0.2.0.dist-info/WHEEL
neuromodex_vnet_dbs-0.2.0.dist-info/licenses/LICENSE
neuromodex_vnet_dbs-0.2.0.dist-info/RECORD
