Metadata-Version: 2.4
Name: neuromodex-vnet-dbs
Version: 0.2.0
Summary: NeuroModex VNet DBS: segmentation and conductivity mapping utilities
Project-URL: Homepage, https://github.com/
Author-email: "FHNW (Michel Ruchti)" <michel.ruchti@fhnw.ch>
License: MIT License
License-File: LICENSE
Keywords: DBS,VNet,deep-learning,medical-imaging,segmentation
Classifier: License :: OSI Approved :: MIT License
Classifier: Operating System :: OS Independent
Classifier: Programming Language :: Python :: 3
Classifier: Topic :: Scientific/Engineering :: Medical Science Apps.
Requires-Python: >=3.9
Requires-Dist: numpy>=2.3.5
Requires-Dist: scipy>=1.16.1
Requires-Dist: simpleitk>=2.5.3
Requires-Dist: torch>=2.9.1
